app/__init__.py
app/__main__.py
app/config.py
app/dialog.py
app/keyboard_listener.py
app/main_window.py
app/mouse_listener.py
app/translator.py
app/images/arrow-turn-000-left.png
app/images/blue-document--plus.png
app/images/cross.png
app/images/exit.png
app/images/highlighter-text.png
app/images/icon.png
app/images/notebook--pencil.png
app/images/swap.png
app/images/window.png
kleantrans-1.0.7.dist-info/LICENSE
kleantrans-1.0.7.dist-info/METADATA
kleantrans-1.0.7.dist-info/WHEEL
kleantrans-1.0.7.dist-info/entry_points.txt
kleantrans-1.0.7.dist-info/top_level.txt
kleantrans-1.0.7.dist-info/RECORD
