Metadata-Version: 2.1
Name: kleantrans
Version: 1.0.7
Summary: Clean and translate your highlight text
Author-email: "Cuong. Duong Manh" <cuongpigerr@gmail.com>
License-File: LICENSE
Requires-Dist: altgraph>=0.17.4
Requires-Dist: packaging==24.1
Requires-Dist: pyinstaller==6.10.0
Requires-Dist: pyinstaller-hooks-contrib>=2024.8
Requires-Dist: pynput>=1.7.7
Requires-Dist: pyperclip>=1.9.0
Requires-Dist: PyQt6>=6.5.0
Requires-Dist: python-xlib>=0.33
Requires-Dist: setuptools>=74.0.0
Requires-Dist: six>=1.16.0
